agentspype/__init__.py
agentspype/agency.py
agentspype/agent/__init__.py
agentspype/agent/agent.py
agentspype/agent/configuration.py
agentspype/agent/definition.py
agentspype/agent/listening.py
agentspype/agent/publishing.py
agentspype/agent/state_machine.py
agentspype/agent/status.py
agentspype-0.1.6.dist-info/LICENSE
agentspype-0.1.6.dist-info/METADATA
agentspype-0.1.6.dist-info/WHEEL
agentspype-0.1.6.dist-info/RECORD
